uniurl/__init__.py
uniurl/__version__.py
uniurl/cli.py
uniurl/core.py
uniurl-1.0.0.dist-info/METADATA
uniurl-1.0.0.dist-info/WHEEL
uniurl-1.0.0.dist-info/entry_points.txt
uniurl-1.0.0.dist-info/top_level.txt
uniurl-1.0.0.dist-info/RECORD
