Metadata-Version: 2.1
Name: uniurl
Version: 1.0.0
Summary: This package takes input from dirsearch tool to remove unused and unworking links
Home-page: https://github.com/bormaa/uniurl
Author: Bormaa
Author-email: ebraammesak@gmail.com
Classifier: Programming Language :: Python :: 3
Classifier: License :: OSI Approved :: MIT License
Classifier: Operating System :: OS Independent
Requires-Python: >=3.6
Requires-Dist: requests (>=2.25.0)
Requires-Dist: fake-useragent (>=1.4.0)
